yaosac.py
yaosac-1.0.1.dist-info/DESCRIPTION.rst
yaosac-1.0.1.dist-info/METADATA
yaosac-1.0.1.dist-info/RECORD
yaosac-1.0.1.dist-info/WHEEL
yaosac-1.0.1.dist-info/metadata.json
yaosac-1.0.1.dist-info/top_level.txt
