Metadata-Version: 2.0
Name: yaosac
Version: 1.0.1
Summary: Yet another OneSignal API Client
Home-page: https://github.com/alej0varas/yaosac
Author: Alexandre Varas
Author-email: alej0varas@gmail.com
License: GNU Library or Lesser General Public License (LGPL)
Keywords: onesignal push notification client api sdk
Platform: UNKNOWN
Classifier: Development Status :: 5 - Production/Stable
Classifier: Intended Audience :: Developers
Classifier: License :: OSI Approved :: GNU Library or Lesser General Public License (LGPL)
Classifier: Operating System :: OS Independent
Classifier: Topic :: Software Development :: Libraries
Classifier: Programming Language :: Python
Classifier: Programming Language :: Python :: 3.5
Requires-Dist: requests
